faketelemetry/__init__.py
faketelemetry/enums.py
faketelemetry/multi_channel.py
faketelemetry/noise_injector.py
faketelemetry/telemetry_generator.py
faketelemetry-0.1.2.dist-info/licenses/LICENSE
faketelemetry-0.1.2.dist-info/METADATA
faketelemetry-0.1.2.dist-info/WHEEL
faketelemetry-0.1.2.dist-info/top_level.txt
faketelemetry-0.1.2.dist-info/RECORD
