Metadata-Version: 2.4
Name: faketelemetry
Version: 0.1.2
Summary: Real-time Fake Telemetry Stream Generator
Home-page: https://github.com/adkvi/faketelemetry
Author: Adam Billekvist
Author-email: adam.billeqvist@gmail.com
Project-URL: Documentation, https://github.com/adkvi/faketelemetry#readme
Project-URL: Source, https://github.com/adkvi/faketelemetry
Project-URL: Tracker, https://github.com/adkvi/faketelemetry/issues
Keywords: telemetry,signal,generator,iot,testing,simulation,waveform,python
Classifier: Programming Language :: Python :: 3
Classifier: License :: OSI Approved :: MIT License
Classifier: Operating System :: OS Independent
Classifier: Intended Audience :: Developers
Classifier: Topic :: Software Development :: Libraries :: Python Modules
Classifier: Topic :: Scientific/Engineering :: Information Analysis
Classifier: Topic :: Software Development :: Testing
Requires-Python: >=3.7
License-File: LICENSE
Dynamic: author
Dynamic: author-email
Dynamic: classifier
Dynamic: description
Dynamic: description-content-type
Dynamic: home-page
Dynamic: keywords
Dynamic: license-file
Dynamic: project-url
Dynamic: requires-python
Dynamic: summary
